s3_storage_provider.py
enhanced_synapse_s3_provider-1.2.50.data/scripts/s3_media_upload
enhanced_synapse_s3_provider-1.2.50.dist-info/LICENSE
enhanced_synapse_s3_provider-1.2.50.dist-info/METADATA
enhanced_synapse_s3_provider-1.2.50.dist-info/WHEEL
enhanced_synapse_s3_provider-1.2.50.dist-info/top_level.txt
enhanced_synapse_s3_provider-1.2.50.dist-info/RECORD
