Metadata-Version: 2.2
Name: enhanced-synapse-s3-provider
Version: 1.2.50
Summary: Enhanced S3 storage provider for Synapse with improved cleanup functionality
Home-page: https://github.com/elyesbenamor/synapse-s3-storage-provider
Author: elyesbenamor
Classifier: Programming Language :: Python :: 3
Classifier: License :: OSI Approved :: Apache Software License
License-File: LICENSE
Requires-Dist: boto3<2.0,>=1.9.23
Requires-Dist: botocore<2.0,>=1.31.62
Requires-Dist: humanize<5.0,>=4.0
Requires-Dist: psycopg2<3.0,>=2.7.5
Requires-Dist: PyYAML<7.0,>=5.4
Requires-Dist: tqdm<5.0,>=4.26.0
Requires-Dist: Twisted
Dynamic: author
Dynamic: classifier
Dynamic: description
Dynamic: description-content-type
Dynamic: home-page
Dynamic: requires-dist
Dynamic: summary
